pyfv/__init__.py
pyfv/fv.py
pyfv/fv_script.py
pyfv/header.py
pyfv/help.py
pyfv/pow.py
pyfv/summary.py
pyfv/table.py
pyfv/utility.py
pyfv/data/sample.image.fits
pyfv/data/sample.table.fits
pyfv/demo/pow.gif
pyfv/docs/2D-Histogram.html
pyfv/docs/3D-ImageDisplay.html
pyfv/docs/3D-ImageTable.html
pyfv/docs/SkyView.html
pyfv/docs/VizieR.html
pyfv/docs/aboutFv.html
pyfv/docs/calculator.html
pyfv/docs/catalog.html
pyfv/docs/columnSelection.html
pyfv/docs/columnStatistics.html
pyfv/docs/connectToHera.html
pyfv/docs/connectToStudentHera.html
pyfv/docs/createNewFITS.html
pyfv/docs/deleteRows.html
pyfv/docs/deskTopManager.html
pyfv/docs/displayDevice.html
pyfv/docs/displayFormat.html
pyfv/docs/expressions.html
pyfv/docs/fileSelection.html
pyfv/docs/fileSummary.html
pyfv/docs/ftool.html
pyfv/docs/fv_scripting.html
pyfv/docs/headerDisplay.html
pyfv/docs/imageDisplay.html
pyfv/docs/imagePlot.html
pyfv/docs/license.html
pyfv/docs/oldscripting.html
pyfv/docs/plotDialog.html
pyfv/docs/preferences.html
pyfv/docs/selectRows.html
pyfv/docs/sortColumn.html
pyfv/docs/startFv.html
pyfv/docs/tableDisplay.html
pyfv-0.0.0a9.dist-info/licenses/LICENSE
pyfv-0.0.0a9.dist-info/METADATA
pyfv-0.0.0a9.dist-info/WHEEL
pyfv-0.0.0a9.dist-info/top_level.txt
pyfv-0.0.0a9.dist-info/RECORD
