Metadata-Version: 2.4
Name: pyfv
Version: 0.0.0a9
Summary: PyFV: modern Python port of FV for FITS image/table viewing and analysis
Author: Pan Chai
License: BSD-3-Clause
Classifier: Programming Language :: Python :: 3
Classifier: License :: OSI Approved :: BSD License
Classifier: Development Status :: 3 - Alpha
Classifier: Intended Audience :: Science/Research
Classifier: Topic :: Scientific/Engineering :: Astronomy
Classifier: Operating System :: OS Independent
Requires-Python: >=3.9
License-File: LICENSE
Dynamic: license-file
